k8s/__init__.py
k8s/io/__init__.py
k8s/io/api/__init__.py
k8s/io/api/core/__init__.py
k8s/io/api/core/v1/__init__.py
k8s/io/api/core/v1/generated_pb2.py
k8s/io/apimachinery/__init__.py
k8s/io/apimachinery/pkg/__init__.py
k8s/io/apimachinery/pkg/api/__init__.py
k8s/io/apimachinery/pkg/api/resource/__init__.py
k8s/io/apimachinery/pkg/api/resource/generated_pb2.py
k8s/io/apimachinery/pkg/apis/__init__.py
k8s/io/apimachinery/pkg/apis/meta/__init__.py
k8s/io/apimachinery/pkg/apis/meta/v1/__init__.py
k8s/io/apimachinery/pkg/apis/meta/v1/generated_pb2.py
k8s/io/apimachinery/pkg/runtime/__init__.py
k8s/io/apimachinery/pkg/runtime/generated_pb2.py
k8s/io/apimachinery/pkg/runtime/schema/__init__.py
k8s/io/apimachinery/pkg/runtime/schema/generated_pb2.py
k8s/io/apimachinery/pkg/util/__init__.py
k8s/io/apimachinery/pkg/util/intstr/__init__.py
k8s/io/apimachinery/pkg/util/intstr/generated_pb2.py
k8s_proto-0.0.2.dist-info/LICENSE
k8s_proto-0.0.2.dist-info/METADATA
k8s_proto-0.0.2.dist-info/NOTICE
k8s_proto-0.0.2.dist-info/WHEEL
k8s_proto-0.0.2.dist-info/top_level.txt
k8s_proto-0.0.2.dist-info/RECORD
