Metadata-Version: 2.1
Name: k8s-proto
Version: 0.0.2
Summary: Generated kubernetes proto code
Home-page: https://github.com/lyft/flyteproto
Maintainer: lyft
Maintainer-email: dev@lyft.com
License: Apache License Version 2.0
Platform: UNKNOWN
Requires-Dist: protobuf (<3.7.0,>=3.6.1)
